riscv-small-v1/ALU.sv
/*
ALU module - 32 bit
32-bits inputs
4-bit Control Signal
Output is 32-bit ALU_result. 
If the ALU_result is zero, zero_flag is set.
*/



module ALU (
    input [31:0] in1,in2, 
    input[3:0] alu_control,
    output reg [31:0] alu_result,
    output reg zero_flag
);
    always @(*)
    begin
        // Operating based on control input
        case(alu_control)

        4'b0000: alu_result = in1&in2;
        4'b0001: alu_result = in1|in2;
        4'b0010: alu_result = in1+in2;
        4'b0100: alu_result = in1-in2;
        4'b1000: begin 
            if(in1<in2)
            alu_result = 1;
            else
            alu_result = 0;
        end
        4'b0011: alu_result = in1<<in2;
        4'b0101: alu_result = in1>>in2;
        4'b0110: alu_result = in1*in2;
        4'b0111: alu_result = in1^in2;

        endcase

        // Setting Zero_flag if ALU_result is zero
        if (alu_result == 0)
            zero_flag = 1'b1;
        else
            zero_flag = 1'b0;
        
    end
endmodule

riscv-small-v1/Reg_file.sv
/*
A register file can read two registers and write in to one register. 
The RISC V register file contains total of 32 registers each of size 32-bit. 
Hence 5-bits are used to specify the register numbers that are to be read or written. 
*/

/*
Register Read: Register file always outputs the contents of the register corresponding to read register numbers specified. 
Reading a register is not dependent on any other signals.

Register Write: Register writes are controlled by a control signal RegWrite.  
Additionally the register file has a clock signal. 
The write should happen if RegWrite signal is made 1 and if there is positive edge of clock. 
*/

module REG_FILE(
    input [4:0] read_reg_num1,
    input [4:0] read_reg_num2,
    input [4:0] write_reg,
    input [31:0] write_data,
    output [31:0] read_data1,
    output [31:0] read_data2,
    input regwrite,
    input clock,
    input reset
);

    reg [31:0] reg_memory [31:0]; // 32 memory locations each 32 bits wide
    integer i=0;

    //  When reset is triggered, we initialize the registers with some values
    always @(posedge reset)
    begin
        // Bear with me for now, I tried using loops, but it won't work
        // Just duct-taping this for now
         reg_memory[0] = 32'h0;
         reg_memory[1] = 32'h1;
         reg_memory[2] = 32'h2;
         reg_memory[3] = 32'h3;
         reg_memory[4] = 32'h4;
         reg_memory[5] = 32'h5;
         reg_memory[6] = 32'h6;
         reg_memory[7] = 32'h7;
         reg_memory[8] = 32'h8;
         reg_memory[9] = 32'h9;
         reg_memory[10] = 32'h10;
         reg_memory[11] = 32'h11;
         reg_memory[12] = 32'h12;
         reg_memory[13] = 32'h13;
         reg_memory[14] = 32'h14;
         reg_memory[15] = 32'h15;
         reg_memory[16] = 32'h16;
         reg_memory[17] = 32'h17;
         reg_memory[18] = 32'h18;
         reg_memory[19] = 32'h19;
         reg_memory[20] = 32'h20;
         reg_memory[21] = 32'h21;
         reg_memory[22] = 32'h22;
         reg_memory[23] = 32'h23;
         reg_memory[24] = 32'h24;
         reg_memory[25] = 32'h25;
		 reg_memory[26] = 32'h26;
         reg_memory[27] = 32'h27;
         reg_memory[28] = 32'h28;
         reg_memory[29] = 32'h29;
         reg_memory[30] = 32'h30;
         reg_memory[31] = 32'h31;

    end

    // The register file will always output the vaules corresponding to read register numbers 
    // It is independent of any other signal
    assign read_data1 = reg_memory[read_reg_num1];
    assign read_data2 = reg_memory[read_reg_num2];

    // If clock edge is positive and regwrite is 1, we write data to specified register
    always @(posedge clock)
    begin

        if (regwrite) begin
            reg_memory[write_reg] = write_data;
        end     
    end

endmodule

riscv-small-v1/Data_Path.sv
`include "Reg_file.sv"
`include "ALU.sv"

module DATAPATH(
    input [4:0]read_reg_num1,
    input [4:0]read_reg_num2,
    input [4:0]write_reg,
    input [3:0]alu_control,
    input regwrite,
    input clock,
    input reset,
    output zero_flag
);

    // Declaring internal wires that carry data
    wire [31:0]read_data1;
    wire [31:0]read_data2;
    wire [31:0]write_data;

    // Instantiating the register file
    REG_FILE reg_file_module(
    read_reg_num1,
    read_reg_num2,
    write_reg,
    write_data,
    read_data1,
    read_data2,
    regwrite,
    clock,
    reset
    );

    // Instanting ALU
    ALU alu_module(read_data1, read_data2, alu_control, write_data, zero_flag);
	 
endmodule

riscv-small-v1/Control.sv
/*
Control Unit for generating control signals for basic ALU processes and datapath.
*/
// Funct3 + Funct7 + Opcode = Instruction
module CONTROL(
    input [6:0] funct7,
    input [2:0] funct3,
    input [6:0] opcode,
    output reg [3:0] alu_control,
    output reg regwrite_control
);
    always @(funct3 or funct7 or opcode) //sens list
    begin
        if (opcode == 7'b0110011) begin // R-type instructions

            regwrite_control = 1;

            case (funct3)
                0: begin
                    if(funct7 == 0)
                    alu_control = 4'b0010; // ADD
                    else if(funct7 == 32)
                    alu_control = 4'b0100; // SUB
                end
                6: alu_control = 4'b0001; // OR
                7: alu_control = 4'b0000; // AND
                1: alu_control = 4'b0011; // SLL
                5: alu_control = 4'b0101; // SRL
				2: alu_control = 4'b0110; // MUL
				4: alu_control = 4'b0111; // XOR
            endcase

      end

    end

endmodule

riscv-small-v1/Instruction_Mem.sv
/* 
Instruction memory takes in two inputs: A 32-bit Program counter and a 1-bit reset. 
The memory is initialized when reset is 1.
When reset is set to 0, Based on the value of PC, corresponding 32-bit Instruction code is output
*/
module INST_MEM(
    input [31:0] PC,
    input reset,
    output [31:0] Instruction_Code
);
    reg [7:0] Memory [31:0]; // Byte addressable memory with 32 locations

    // Under normal operation (reset = 0), we assign the instr. code, based on PC
    assign Instruction_Code = {Memory[PC+3],Memory[PC+2],Memory[PC+1],Memory[PC]};

    // Initializing memory when reset is one
    always @(reset)
    begin
        if(reset == 1)
        begin
            // Setting 32-bit instruction: add t1, s0,s1 => 0x00940333 
            Memory[3] = 8'h00;
            Memory[2] = 8'h94;
            Memory[1] = 8'h03;
            Memory[0] = 8'h33;
            // Setting 32-bit instruction: sub t2, s2, s3 => 0x413903b3
            Memory[7] = 8'h41;
            Memory[6] = 8'h39;
            Memory[5] = 8'h03;
            Memory[4] = 8'hb3;
            // Setting 32-bit instruction: mul t0, s4, s5 => 0x035a02b3
            Memory[11] = 8'h03;
            Memory[10] = 8'h5a;
            Memory[9] = 8'h02;
            Memory[8] = 8'hb3;
            // Setting 32-bit instruction: xor t3, s6, s7 => 0x017b4e33
            Memory[15] = 8'h01;
            Memory[14] = 8'h7b;
            Memory[13] = 8'h4e;
            Memory[12] = 8'h33;
            // Setting 32-bit instruction: sll t4, s8, s9
            Memory[19] = 8'h01;
            Memory[18] = 8'h9c;
            Memory[17] = 8'h1e;
            Memory[16] = 8'hb3;
            // Setting 32-bit instruction: srl t5, s10, s11
            Memory[23] = 8'h01;
            Memory[22] = 8'hbd;
            Memory[21] = 8'h5f;
            Memory[20] = 8'h33;
            // Setting 32-bit instruction: and t6, a2, a3
            Memory[27] = 8'h00;
            Memory[26] = 8'hd6;
            Memory[25] = 8'h7f;
            Memory[24] = 8'hb3;
            // Setting 32-bit instruction: or a7, a4, a5
            Memory[31] = 8'h00;
            Memory[30] = 8'hf7;
            Memory[29] = 8'h68;
            Memory[28] = 8'hb3;
        end
    end

endmodule

riscv-small-v1/IFU.sv
/*
The instruction fetch unit has clock and reset pins as input and 32-bit instruction code as output.
Internally the block has Instruction Memory, Program Counter(P.C) and an adder to increment counter by 4, 
on every positive clock edge.
*/
`include "Instruction_Mem.sv"

module IFU(
    input clock,reset,
    output [31:0] Instruction_Code
);
reg [31:0] PC = 32'b0;  // 32-bit program counter is initialized to zero

    // Initializing the instruction memory block
    INST_MEM instr_mem(PC,reset,Instruction_Code);

    always @(posedge clock, posedge reset)
    begin
        if(reset == 1)  //If reset is one, clear the program counter
        PC <= 0;
        else
        PC <= PC+4;   // Increment program counter on positive clock edge
    end

endmodule

riscv-small-v1/CPU.sv
//-----------------------------------------------------------------
//--------------------------------------------------------------------
// Small RISC-V
// ALU, DATAPATH, CONTROL UNIT, IF/ID, ID/EX, EX/MEM, MEM/WB, NO STALL UNIT
//--------------------------------------------------------------------

`include "Control.sv"
`include "Data_Path.sv"
`include "IFU.sv"

module PROCESSOR( 
    input clock, 
    input reset,
    output zero
);

    wire [31:0] instruction_code;
    wire [3:0] alu_control;
    wire regwrite;

    IFU IFU_module(clock, reset, instruction_code);
	
    CONTROL control_module(instruction_code[31:25], instruction_code[14:12],instruction_code[6:0], alu_control, regwrite);
	
    DATAPATH datapath_module(instruction_code[19:15], instruction_code[24:20], instruction_code[11:7], alu_control, regwrite, clock, reset, zero);

endmodule

riscv-small-v1/CPU_tb.sv
`include "CPU.sv"

module stimulus ();
    
    reg clock;
    reg reset;
    wire zero;

    // Instantiating the processor!!!
    PROCESSOR test_processor(clock,reset,zero);

    initial begin
        $dumpfile("output_wave.vcd");
        $dumpvars(0,stimulus);
    end

    initial begin
        reset = 1;
        #50 reset = 0;
    end

    initial begin
        clock = 0;
        forever #20 clock = ~clock;
    end

    initial
    #300 $finish;
    
endmodule

riscv-small-v1/output_wave.vcd
$date
	Fri Jan 26 12:14:23 2024
$end
$version
	Icarus Verilog
$end
$timescale
	1s
$end
$scope module stimulus $end
$var wire 1 ! zero $end
$var reg 1 " clock $end
$var reg 1 # reset $end
$scope module test_processor $end
$var wire 1 " clock $end
$var wire 1 # reset $end
$var wire 1 ! zero $end
$var wire 1 $ regwrite $end
$var wire 32 % instruction_code [31:0] $end
$var wire 4 & alu_control [3:0] $end
$scope module IFU_module $end
$var wire 1 " clock $end
$var wire 1 # reset $end
$var wire 32 ' Instruction_Code [31:0] $end
$var reg 32 ( PC [31:0] $end
$scope module instr_mem $end
$var wire 32 ) PC [31:0] $end
$var wire 1 # reset $end
$var wire 32 * Instruction_Code [31:0] $end
$upscope $end
$upscope $end
$scope module control_module $end
$var wire 3 + funct3 [2:0] $end
$var wire 7 , funct7 [6:0] $end
$var wire 7 - opcode [6:0] $end
$var reg 4 . alu_control [3:0] $end
$var reg 1 $ regwrite_control $end
$upscope $end
$scope module datapath_module $end
$var wire 4 / alu_control [3:0] $end
$var wire 1 " clock $end
$var wire 5 0 read_reg_num1 [4:0] $end
$var wire 5 1 read_reg_num2 [4:0] $end
$var wire 1 $ regwrite $end
$var wire 1 # reset $end
$var wire 5 2 write_reg [4:0] $end
$var wire 1 ! zero_flag $end
$var wire 32 3 write_data [31:0] $end
$var wire 32 4 read_data2 [31:0] $end
$var wire 32 5 read_data1 [31:0] $end
$scope module alu_module $end
$var wire 4 6 alu_control [3:0] $end
$var wire 32 7 in2 [31:0] $end
$var wire 32 8 in1 [31:0] $end
$var reg 32 9 alu_result [31:0] $end
$var reg 1 ! zero_flag $end
$upscope $end
$scope module reg_file_module $end
$var wire 1 " clock $end
$var wire 32 : read_data1 [31:0] $end
$var wire 32 ; read_data2 [31:0] $end
$var wire 5 < read_reg_num1 [4:0] $end
$var wire 5 = read_reg_num2 [4:0] $end
$var wire 1 $ regwrite $end
$var wire 1 # reset $end
$var wire 32 > write_data [31:0] $end
$var wire 5 ? write_reg [4:0] $end
$var integer 32 @ i [31:0] $end
$upscope $end
$upscope $end
$upscope $end
$upscope $end
$enddefinitions $end
$comment Show the parameter values. $end
$dumpall
$end
#0
$dumpvars
b0 @
b110 ?
b10001 >
b1001 =
b1000 <
b1001 ;
b1000 :
b10001 9
b1000 8
b1001 7
b10 6
b1000 5
b1001 4
b10001 3
b110 2
b1001 1
b1000 0
b10 /
b10 .
b110011 -
b0 ,
b0 +
b100101000000001100110011 *
b0 )
b0 (
b100101000000001100110011 '
b10 &
b100101000000001100110011 %
1$
1#
0"
0!
$end
#20
1"
#40
0"
#50
0#
#60
b100 &
b100 .
b100 /
b100 6
b11111111111111111111111111111111 3
b11111111111111111111111111111111 9
b11111111111111111111111111111111 >
b100000 ,
b11001 4
b11001 7
b11001 ;
b10011 1
b10011 =
b11000 5
b11000 8
b11000 :
b10010 0
b10010 <
b111 2
b111 ?
b1000001001110010000001110110011 %
b1000001001110010000001110110011 '
b1000001001110010000001110110011 *
b100 (
b100 )
1"
#80
0"
#100
b1 ,
b100001 4
b100001 7
b100001 ;
b10101 1
b10101 =
b100000 5
b100000 8
b100000 :
b10100 0
b10100 <
b101 2
b101 ?
b11010110100000001010110011 %
b11010110100000001010110011 '
b11010110100000001010110011 *
b1000 (
b1000 )
1"
#120
0"
#140
b1 3
b1 9
b1 >
b111 &
b111 .
b111 /
b111 6
b0 ,
b100011 4
b100011 7
b100011 ;
b10111 1
b10111 =
b100010 5
b100010 8
b100010 :
b10110 0
b10110 <
b100 +
b11100 2
b11100 ?
b1011110110100111000110011 %
b1011110110100111000110011 '
b1011110110100111000110011 *
b1100 (
b1100 )
1"
#160
0"
#180
1!
b0 3
b0 9
b0 >
b11 &
b11 .
b11 /
b11 6
b100101 4
b100101 7
b100101 ;
b11001 1
b11001 =
b100100 5
b100100 8
b100100 :
b11000 0
b11000 <
b1 +
b11101 2
b11101 ?
b1100111000001111010110011 %
b1100111000001111010110011 '
b1100111000001111010110011 *
b10000 (
b10000 )
1"
#200
0"
#220
b101 &
b101 .
b101 /
b101 6
b100111 4
b100111 7
b100111 ;
b11011 1
b11011 =
b100110 5
b100110 8
b100110 :
b11010 0
b11010 <
b101 +
b11110 2
b11110 ?
b1101111010101111100110011 %
b1101111010101111100110011 '
b1101111010101111100110011 *
b10100 (
b10100 )
1"
#240
0"
#260
0!
b10010 3
b10010 9
b10010 >
b0 &
b0 .
b0 /
b0 6
b10011 4
b10011 7
b10011 ;
b1101 1
b1101 =
b10010 5
b10010 8
b10010 :
b1100 0
b1100 <
b111 +
b11111 2
b11111 ?
b110101100111111110110011 %
b110101100111111110110011 '
b110101100111111110110011 *
b11000 (
b11000 )
1"
#280
0"
#300
b10101 3
b10101 9
b10101 >
b1 &
b1 .
b1 /
b1 6
b10101 4
b10101 7
b10101 ;
b1111 1
b1111 =
b10100 5
b10100 8
b10100 :
b1110 0
b1110 <
b10001 2
b10001 ?
b110 +
b111101110110100010110011 %
b111101110110100010110011 '
b111101110110100010110011 *
b11100 (
b11100 )
1"
